flexibuddiesrl/Agent.py
flexibuddiesrl/Agent_spec.py
flexibuddiesrl/DDPG.py
flexibuddiesrl/DQN.py
flexibuddiesrl/DQN_spec.py
flexibuddiesrl/PG.py
flexibuddiesrl/PG_spec.py
flexibuddiesrl/PG_stabalized.py
flexibuddiesrl/SAC.py
flexibuddiesrl/SAC_spec.py
flexibuddiesrl/TD3.py
flexibuddiesrl/Util.py
flexibuddiesrl/__init__.py
flexibuddiesrl/models_spec.py
flexibuddiesrl/test.py
flexibuddiesrl-0.4.14.dist-info/METADATA
flexibuddiesrl-0.4.14.dist-info/WHEEL
flexibuddiesrl-0.4.14.dist-info/RECORD
