Metadata-Version: 2.4
Name: flexibuddiesrl
Version: 0.4.14
Summary: An Agent API for MARL research that is compatible with flexibuff and flexirunner
Project-URL: Homepage, https://github.com/Timothy-Flavin/FlexiBuddiesRL/
Project-URL: Bug Tracker, https://github.com/Timothy-Flavin/FlexiBuddiesRL/issues
Author-email: Timothy Flavin <timothy.c.flavin@gmail.com>
Classifier: License :: OSI Approved :: GNU General Public License v2 (GPLv2)
Classifier: Operating System :: OS Independent
Classifier: Programming Language :: Python :: 3
Requires-Python: >=3.7
